pymtools/__init__.py
pymtools/colors.py
pymtools/exports.py
pymtools/ext.py
pymtools/misc.py
pymtools/net.py
pymtools/opsys.py
pymtools-0.1.1b0.dist-info/METADATA
pymtools-0.1.1b0.dist-info/WHEEL
pymtools-0.1.1b0.dist-info/licenses/LICENCE.md
pymtools-0.1.1b0.dist-info/RECORD
