Metadata-Version: 2.1
Name: pymtools
Version: 0.1.1b0
Summary: Miscellaneous tools for Python
Project-URL: Author repository, https://github.com/Backist/
Project-URL: repository, https://github.com/Backist/Misctools
Project-URL: Bug issues, https://github.com/Backist/Misctools/issues
Author-email: Alvaro Monllor <alvarodrumer54@gmail.com>
License:                     GNU GENERAL PUBLIC LICENSE
License-File: LICENCE.md
Keywords: Miscellaneous tools,Python,Python-tools,Python3
Classifier: Development Status :: 4 - Beta
Classifier: License :: OSI Approved :: GNU General Public License v3 or later (GPLv3+)
Classifier: Natural Language :: Spanish
Classifier: Operating System :: Microsoft :: Windows :: Windows 10
Classifier: Operating System :: Microsoft :: Windows :: Windows 11
Classifier: Programming Language :: Python :: 3.10
Classifier: Programming Language :: Python :: 3.11
Classifier: Typing :: Typed
Requires-Python: >=3.10.2
Requires-Dist: chardet>=4.0.0
Requires-Dist: colorama>=0.4.4
Requires-Dist: csv>=0.0.0
Requires-Dist: matplotlib~=3.5.2
Requires-Dist: pillow~=9.0.1
Requires-Dist: psutil>=5.9.0
Requires-Dist: toml>=0.10.0
Requires-Dist: xmltodict
Provides-Extra: dev
Requires-Dist: typing-extensions~=3.7.4; extra == 'dev'
